{"接种仪": {"GS-360型全自动螺旋接种仪": ["包装", "制药/生物医药", "医疗/健康", "石油化工", "环保"], "DW-16型 自动细菌涂布接种仪": ["农业", "医疗/健康", "食品", "环保"], "杭州华端 HD-L2型 自动细菌涂布仪 药敏涂布仪": ["农业", "其他", "医疗/健康", "食品", "环保"], "华端HD-MS200自动菌液接种加样仪": ["其他", "医疗/健康", "食品"], "DW-6型 细菌接种环灭菌器（电热红外）": ["其他", "食品"], "华端HD-MS100自动菌液接种加样仪": ["其他", "医疗/健康", "食品"], "恒奥细菌多点接种仪HMI-60/24": ["医疗/健康", "环保"], "WIGGENS Sensorturn 培养皿自动转盘": ["医疗/健康", "化妆品", "食品", "环保"], "interscience easySpiral螺旋细菌接种仪": ["医疗/健康"]}, "微生物鉴定系统": {"微生物快速检测系统": ["制药/生物医药", "医疗/健康", "生物研究", "食品"], "Axcess® MALDI-TOF微生物鉴定系统": ["制药/生物医药", "电子/电气", "环保", "生物研究", "食品"], "临床单细胞拉曼药敏性快检仪 CAST-R": ["制药/生物医药", "医疗/健康", "生物研究"], "AUTOPET克隆菌落挑选仪": ["制药/生物医药", "医疗/健康", "环保", "食品"], "沙门氏菌快速检测仪": ["化妆品", "农业", "医疗/健康", "环保", "食品"], "金黄色葡萄球菌快速检测仪": ["化妆品", "医疗/健康", "环保", "食品"], "Wormseek两虫检测系统": ["地矿", "农业", "环保", "食品"], "德瑞克 DRK1070 阻干态微生物穿透测试仪": ["纺织/印染", "医疗/健康", "生物研究"], "全自动微生物质谱鉴定系统": ["农业", "医疗/健康", "其他", "环保", "生物研究", "食品"], "MBS（Fitlylab）饲料致病菌快速检测系统": ["农业", "其他", "环保", "生物研究", "食品"], "食源性微生物致病菌检测仪": ["农业", "医疗/健康", "生物研究", "食品"], "新芝scientz微生物生长曲线分析仪MGC-500": ["农业", "医疗/健康", "其他", "环保", "生物研究", "食品"], "新芝scientz微生物生长曲线分析仪MGC-200": ["医疗/健康", "其他", "食品"], "IDEXX OSB-8 Plus两虫升级版快速取样箱": ["医疗/健康", "环保", "生物研究"], "SimPlate酶底物法检测菌落总数": ["医疗/健康", "环保", "生物研究", "食品"], "高通量菌落智能筛选系统": ["医疗/健康", "其他", "环保", "生物研究", "食品"], "全自动微生物质谱检测系统（质谱仪）": ["医疗/健康", "环保", "生物研究", "食品"], "8通道克隆菌落挑选仪": ["医疗/健康", "环保", "食品"], "Enterolert肠球菌检测试剂盒": ["医疗/健康", "环保", "生物研究", "食品"], "Pseudalert铜绿假单胞菌检测试剂盒": ["医疗/健康", "环保", "生物研究", "食品"], "RICKA GCT-23A智慧型两虫滤膜浓缩/密度梯度法检测系统": ["医疗/健康", "环保", "生物研究"], "EZ DPD总氯/余氯检测试剂": ["医疗/健康", "环保", "生物研究", "食品"], "贾第鞭毛虫和隐孢子虫检测系统 Filta-max xpress": ["食品"], "RICKA GCR-23A智慧型两虫检测读数仪": ["医疗/健康", "环保", "生物研究"], "Legiolert定量检测嗜肺军团菌": ["医疗/健康", "环保", "生物研究", "食品"], "华端生物HD-MA200型自动微生物鉴定及药敏分析系统": ["医疗/健康", "生物研究"], "自动细菌涂布仪 药敏涂布仪": ["医疗/健康", "生物研究"], "华端生物HD-F3型水中微生物膜过滤装置": ["医疗/健康", "环保", "生物研究", "食品"], "全自动划线接种仪": ["其他"], "HD-MA300型自动微生物生化鉴定及药敏分析系统": ["其他"], "华端 HD-MA100型自动微生物生化鉴定系统": ["其他", "生物研究", "食品"], "华端生物HD-M-Discover微生物质谱鉴定系统": ["其他", "环保", "食品"], "奎泰斯特-全自动两虫检测系统": ["环保", "生物研究"], "泽析生物MAS-H2生物综合分析联用仪、藻类自动计数仪": ["环保", "食品"], "酶底物法 粪大肠菌群检测系统 程控定量封口机": ["环保", "生物研究"], "奎泰斯特-两虫检测系统": ["环保", "生物研究"], "泽析生物MAS-H1生物综合联用仪浮游生物智能鉴定计数仪": ["环保", "食品"]}, "大肠杆菌检测仪": {"程控定量封口机": ["制药/生物医药", "其他", "生物研究", "医疗/健康", "环保", "食品", "农业"], "酶底物法程控定量封口机": ["制药/生物医药", "生物研究", "医疗/健康", "环保", "食品", "农业"], "肠杆菌科快速检测仪": ["制药/生物医药", "医疗/健康", "环保", "食品", "农业"], "大肠杆菌检测仪云唐微生物检测仪": ["其他", "生物研究", "环保", "食品", "农业"], "大肠杆菌检测仪": ["其他", "生物研究", "医疗/健康", "环保", "食品"], "微生物全自动检测仪": ["生物研究", "医疗/健康", "环保", "食品"], "大肠杆菌/大肠菌群检测仪": ["生物研究", "医疗/健康", "环保", "食品", "农业"], "酶底物法": ["生物研究", "医疗/健康", "环保", "食品"], "大肠埃希氏菌快速检测": ["生物研究", "医疗/健康", "环保", "食品"], "科立得": ["生物研究", "医疗/健康", "环保", "食品"], "97孔定量盘": ["生物研究", "医疗/健康", "环保", "食品"], "爱德士 DST大肠菌群检测系统 程控定量封口机": ["生物研究", "医疗/健康", "环保", "食品"], "爱德士大肠菌群检测系统 程控定量封口机": ["生物研究", "医疗/健康", "环保", "食品"], "爱德士 51孔定量盘 程控定量封口机": ["生物研究", "医疗/健康", "环保", "食品"], "爱德士科立得 检测粪大肠菌群 WCHN200 程控定量封口机": ["生物研究", "医疗/健康", "环保", "食品"], "97孔阳性比色盘": ["生物研究", "医疗/健康", "环保", "食品"], "微生物检测系统": ["医疗/健康", "食品"], "程控定量封口机 9900z sealer plus": ["医疗/健康", "环保", "食品"], "酶底物法 程控定量封口机 大肠菌群检测系统": ["环保"], "意大利MBS微生物快速检测仪": ["食品"]}, "微生物限度仪": {"Modern Water QuickChek SRB 硫酸盐还原菌检测系统": ["汽车制造", "交通", "钢铁", "石油化工", "环保"], "赛多利斯 Microsart® 过滤支架": ["制药/生物医药", "食品"], "MBS微生物检测系统/微生物检测仪": ["制药/生物医药", "生物研究", "农业", "环保", "食品"], "新芝scientz全自动微生物生长曲线分析仪SCIENTZ-WSQ": ["制药/生物医药", "医疗/健康", "生物研究", "农业"], "点成DEN-1B麦氏比浊仪": ["制药/生物医药", "医疗/健康", "生物研究", "环保"], "微生物限度检测仪": ["制药/生物医药", "生物研究", "环保", "食品"], "Celsis 微生物快速检测系统": ["制药/生物医药", "生物研究", "食品"], "QIS-301微生物限度检测仪": ["制药/生物医药", "医疗/健康", "环保"], "六联微生物限度检测仪 细菌薄膜过滤器 微生物限度检查仪": ["其他", "医疗/健康", "生物研究", "食品"], "生物发酵生化样品自动处理分析仪MBP": ["其他", "石油化工", "医疗/健康", "生物研究", "农业", "环保", "食品"], "微生物限度检测仪,微生物限度检查仪,微生物限度仪": ["其他", "石油化工", "医疗/健康", "生物研究", "农业", "环保", "食品"], "微生物限度检测仪CYW-300B一体式内置泵": ["其他", "医疗/健康", "生物研究", "农业", "环保"], "智能细胞荧光分析仪": ["其他", "生物研究"], "便携式微生物鉴定系统": ["其他", "生物研究"], "图旺微生物限度过滤系统 薄膜过滤系统TW-602C": ["其他", "石油化工", "医疗/健康", "生物研究", "农业", "环保", "食品"], "华端生物HD-F6型水中微生物膜过滤装置": ["其他", "石油化工", "医疗/健康", "生物研究", "农业", "环保", "食品"], "赛多利斯过滤支架 Microsart® Combi.jet": ["食品"], "微生物发酵在线检测仪BODS科研版": ["其他", "环保", "生物研究", "食品"], "图旺微生物限度过滤系统TW-402C 滤膜过滤系统": ["其他", "石油化工", "农业", "环保", "医疗/健康", "生物研究", "食品"], "图旺微生物限度过滤系统TW-302C 微生物限度检测仪、微生物薄膜过滤器": ["其他", "石油化工", "农业", "环保", "医疗/健康", "生物研究", "食品"], "图旺微生物限度过滤系统,微生物检测仪TW-202C、微生物薄膜过滤器": ["其他", "石油化工", "农业", "医疗/健康", "环保", "生物研究", "食品"], "图旺微生物限度过滤支架TW-STV6A": ["其他", "石油化工", "农业", "医疗/健康", "环保", "生物研究", "食品"], "华端生物HD-F3型水中微生物膜过滤装置": ["其他", "医疗/健康", "环保", "生物研究", "食品"], "图旺内镜微生物检测仪TW-101N": ["其他", "石油化工", "农业", "医疗/健康", "环保", "生物研究", "食品"], "图旺内镜检测取样泵TW-WP02N": ["其他", "石油化工", "农业", "医疗/健康", "环保", "生物研究", "食品"], "华端生物HD-F6P型微生物过滤检测系统": ["其他", "医疗/健康", "环保", "生物研究", "食品"], "微生物限度仪DW-H305型": ["石油化工", "医疗/健康", "生物研究", "农业", "食品"], "微生物限度仪 LM-G308型": ["石油化工", "医疗/健康", "农业", "食品"], "生物培养过程在线监测仪": ["石油化工", "医疗/健康", "生物研究"], "药品微生物限度检查,适用于食品饮料啤酒企业原料,半成品和成品的实验室微生物检测": ["石油化工", "医疗/健康", "生物研究", "环保", "食品"], "微生物限度仪DW-S301型": ["石油化工", "医疗/健康", "生物研究", "食品"], "微生物限度仪DW-H303型": ["石油化工", "医疗/健康", "生物研究", "农业", "食品"], "微生物限度仪LM-S601P型": ["石油化工", "医疗/健康", "农业", "食品"], "微生物限度仪LM-G608型": ["石油化工", "农业", "医疗/健康", "食品"], "赛多利斯 Sterisart® Universal 第四代无菌检测泵": ["医疗/健康", "生物研究"], "微生物检测仪 优云谱 肠道菌群检测仪器": ["医疗/健康", "生物研究", "环保", "食品"], "Sievers SOLEIL 快速生物负载分析仪": ["医疗/健康", "生物研究", "食品"], "Sievers Soleil快速微生物检测仪": ["医疗/健康", "生物研究", "农业", "环保", "食品"], "液晶微生物限度机检测仪，微生物水样过滤装置": ["医疗/健康", "生物研究", "食品"], "默克 Millipore® Oasis微生物过滤系统 微生物检测系统": ["医疗/健康", "生物研究", "环保", "食品"], "DW-28型水中微生物膜过滤装置": ["医疗/健康", "环保", "食品"], "封闭式微生物检测仪JTW-300B滤头可单独控制": ["医疗/健康", "生物研究", "环保"], "全自动生长曲线分析仪": ["医疗/健康", "生物研究", "食品"], "日本Antares微生物代谢微反应热测试系统": ["医疗/健康", "生物研究", "农业", "食品"], "微生物限度检验仪QIS-606": ["医疗/健康", "环保"], "微生物限度检测仪HTY-305SP": ["医疗/健康", "环保", "食品"], "微生物限度仪DW-S301P型": ["医疗/健康", "生物研究", "环保", "食品"], "微生物限度仪DW-S302型": ["医疗/健康", "生物研究", "环保", "食品"], "微生物克隆筛选系统QPix 400": ["农业"], "抗生素荧光定量检测仪": ["农业", "食品"], "Charm EPIC  商业无菌快速检测仪": ["农业", "食品"], "多参数生化样品自动处理分析仪MBP": ["农业", "环保", "医疗/健康", "生物研究"], "胶体金读卡仪DY6260": ["农业", "食品"], "Charm Peel Plate菌落计数仪": ["农业", "食品"], "Evergreen MS-GDS免疫磁珠分离快速检测系统": ["农业", "食品"], "微生物限度仪LM-Z300支架型": ["环保", "医疗/健康", "生物研究"], "内置泵微生物限度检测仪": ["环保", "医疗/健康", "食品"], "新DW-100A-K型智能厌氧培养系统/厌氧工作站": ["环保", "医疗/健康", "生物研究", "食品"], "DW-18型 快速生物监测培养仪": ["环保", "医疗/健康", "生物研究", "食品"], "DW-100A-K2智能厌氧微生物培养系统": ["环保", "医疗/健康", "生物研究", "食品"], "纯化水过滤过滤装置JTW-600B悬浮物微生物限度仪": ["环保", "医疗/健康", "食品"], "赛多利斯 Microsart® E-motion 滤膜分配器": ["食品"], "赛多利斯 Microsart® E-jet 直排泵": ["食品"], "微生物限度仪LM-Z600支架型": ["医疗/健康", "生物研究", "食品"], "DW-ES800型微生物实时检测系统": ["医疗/健康", "生物研究", "食品"], "微生物限度过滤系统JTW-100S迷你型设计": ["医疗/健康", "生物研究", "食品"], "启鲲QIS-303S微生物限度检验仪": ["医疗/健康"]}, "菌落计数仪": {"舒特Schuett ColonyQuant全自动菌落计数仪": ["农业", "烟草", "生物研究", "医疗/健康"], "洛科仪器galaxy330手动菌落计数器": ["农业", "生物研究", "环保", "食品", "制药/生物医药"], "微生物检测菌落计数器分析仪MBS.SRL": ["农业", "钢铁", "化妆品", "其他", "环保", "医疗/健康", "食品", "制药/生物医药"], "迅数MF1显微分析多功能联用仪": ["农业", "医疗/健康"], "洛科仪器 Galaxy 330  菌落计数器": ["生物研究", "化妆品", "医疗/健康", "食品", "制药/生物医药"], "NooneLost-3000型全自动显微/菌落计数": ["生物研究", "环保", "医疗/健康", "食品"], "菌落计数器  Galaxy331": ["生物研究", "环保", "医疗/健康", "食品"], "青岛路博便携式全自动菌落计数仪LB-6300": ["钢铁", "环保", "医疗/健康", "食品", "制药/生物医药"], "MR-A20 微生物快速检测系统": ["钢铁", "其他", "环保", "医疗/健康", "食品", "制药/生物医药"], "菌落计数分析仪": ["钢铁", "其他", "环保", "医疗/健康", "食品", "制药/生物医药"], "自动菌落计数仪SHASHIN KAGAKU": ["钢铁", "其他", "环保", "医疗/健康", "食品", "制药/生物医药"], "菌落计数/筛选/抑菌圈测量联用仪": ["钢铁", "食品"], "迅数icount 33全自动菌落计数仪": ["钢铁", "环保", "医疗/健康", "食品", "制药/生物医药"], "程控定量封口机、酶底物法程控定量封口机": ["钢铁", "其他", "环保", "医疗/健康", "制药/生物医药", "食品"], "迅数FLuo2荧光菌落分析仪": ["钢铁", "其他", "环保", "医疗/健康", "食品", "制药/生物医药"], "WIGGENS  Galaxy 230 菌落计数器": ["其他", "环保", "医疗/健康", "食品", "制药/生物医药"], "HD1000 AI智能菌落计数仪": ["其他", "环保", "食品", "制药/生物医药"], "动态菌落计数系统": ["其他", "环保", "医疗/健康", "食品", "制药/生物医药"], "自动菌落计数仪": ["其他", "食品", "制药/生物医药"], "华端 HD-C3型-菌落计数器感应压力计数": ["其他"], "Czone 12  AI智能菌落计数及抑菌圈测量仪": ["其他", "环保", "食品", "制药/生物医药"], "ZR-1101型 全自动菌落计数仪": ["环保", "制药/生物医药"], "新MF3显微分析、菌落计数、抑菌圈联用仪": ["环保", "制药/生物医药"], "泽析生物ZX-400型全自动菌落计数仪，自动菌落分析仪": ["环保", "医疗/健康", "食品"], "恒奥菌落计数器HCC": ["环保", "食品"], "全自动菌落计数器": ["环保", "医疗/健康", "食品", "制药/生物医药"], "interscience  Scan型 全自动菌落计数仪": ["环保", "医疗/健康", "食品"], "环凯自动菌落计数仪SmartCounter-4K": ["环保", "医疗/健康", "食品", "制药/生物医药"], "德淙全自动拉曼菌落挑选工作站Autopet-CPS": ["环保", "医疗/健康", "食品", "制药/生物医药"], "迅数icount 50全自动菌落计数仪": ["环保", "医疗/健康", "食品", "制药/生物医药"], "Czone 9 / Czone 9 pro菌落计数及抑菌圈测量仪": ["环保", "医疗/健康", "食品", "制药/生物医药"], "迅数icount 22 全自动菌落计数仪": ["环保", "医疗/健康", "食品"], "Supcre G10（AI） 菌落计数/筛选/抑菌圈测量联用仪": ["环保", "医疗/健康", "食品", "制药/生物医药"], "迅数icount 60/ icount 60pro全自动菌落计数仪": ["环保", "医疗/健康", "制药/生物医药", "食品"], "HD5000（AI）多谱超分辨菌落成像系统": ["环保", "医疗/健康", "制药/生物医药", "食品"], "MAS-HL生物综合联用仪，浮游动物鉴定计数仪藻类计数仪": ["环保", "医疗/健康", "制药/生物医药", "食品"], "DW-2型菌落计数器": ["医疗/健康", "食品", "制药/生物医药"], "迅数MF6菌落计数/显微分析多功能联用仪": ["医疗/健康"], "泽析生物效价测量自动菌落计数仪，自动抑菌圈测量仪": ["医疗/健康", "制药/生物医药"], "恒奥全自动菌落计数器HCC-90A": ["食品"], "菌落计数器": ["食品"], "迅数MF4菌落计数/显微分析多功能联用仪": ["食品", "制药/生物医药"], "迅数icount 11 全自动菌落计数仪": ["食品"], "Supcre G9菌落计数/筛选/抑菌圈测量联用仪": ["制药/生物医药"], "迅数Czone 8菌落计数及抑菌圈测量仪": ["制药/生物医药"], "迅数MF5菌落计数/显微分析多功能联用仪": ["制药/生物医药"], "泽析生物ZX-300型全自动菌落计数仪，菌落分析计数仪": ["环保", "医疗/健康", "食品"], "泽析生物ZX-100型全自动菌落计数器": ["环保", "医疗/健康", "食品"], "HD2000（AI）智能菌落计数仪": ["医疗/健康", "食品", "制药/生物医药"], "DW-V型全自动菌落计数仪": ["医疗/健康", "食品", "制药/生物医药"], "泽析生物ZX-200型全自动自动菌落成像分析系统": ["医疗/健康", "食品", "制药/生物医药"]}, "发酵分析仪": {"生物发酵尾气分析仪 FERMENT1000": ["生物研究"]}}